Metadata-Version: 1.0
Name: ep2
Version: 22.1.2
Summary: This is test package to learn distribution on open source
Home-page: UNKNOWN
Author: EP
Author-email: UNKNOWN
License: UNKNOWN
Platform: UNKNOWN
